gatey_sdk/__init__.py
gatey_sdk/__version__.py
gatey_sdk/api.py
gatey_sdk/auth.py
gatey_sdk/buffer.py
gatey_sdk/client.py
gatey_sdk/consts.py
gatey_sdk/exceptions.py
gatey_sdk/integrations/__init__.py
gatey_sdk/integrations/django.py
gatey_sdk/integrations/flask.py
gatey_sdk/integrations/starlette.py
gatey_sdk/internal/__init__.py
gatey_sdk/internal/exc.py
gatey_sdk/internal/source.py
gatey_sdk/internal/traceback.py
gatey_sdk/py.typed
gatey_sdk/response.py
gatey_sdk/transports/__init__.py
gatey_sdk/transports/base.py
gatey_sdk/transports/func.py
gatey_sdk/transports/http.py
gatey_sdk/transports/print.py
gatey_sdk/transports/void.py
gatey_sdk/utils.py
gatey_sdk-0.0.11.dist-info/LICENSE
gatey_sdk-0.0.11.dist-info/METADATA
gatey_sdk-0.0.11.dist-info/WHEEL
gatey_sdk-0.0.11.dist-info/RECORD
