Metadata-Version: 2.1
Name: gatey-sdk
Version: 0.0.11
Summary: Python client for Gatey (https://gatey.florgon.com)
License: MIT
Author: Florgon Team and Contributors
Requires-Python: >=3.7,<4.0
Classifier: License :: OSI Approved :: MIT License
Classifier: Programming Language :: Python :: 3
Classifier: Programming Language :: Python :: 3.7
Classifier: Programming Language :: Python :: 3.8
Classifier: Programming Language :: Python :: 3.9
Classifier: Programming Language :: Python :: 3.10
Classifier: Programming Language :: Python :: 3.11
Classifier: Programming Language :: Python :: 3.12
Requires-Dist: requests (>=2.28.1,<3.0.0)
